cli/__init__.py
cli/__main__.py
cli/config.py
cli/project.py
cli/cmd/__init__.py
cli/cmd/base.py
cli/cmd/init.py
cli/cmd/profile.py
cli/cmd/run.py
cli/parsers/__init__.py
cli/parsers/monitors.py
cli/utils/__init__.py
cli/utils/files.py
cli/utils/yaml.py
core/__init__.py
core/common/__init__.py
core/common/events.py
core/common/drivers/__init__.py
core/common/drivers/base.py
core/common/drivers/column.py
core/common/drivers/factory.py
core/common/drivers/postgres/__init__.py
core/common/drivers/postgres/configuration.py
core/common/drivers/postgres/dialect.py
core/common/drivers/postgres/driver.py
core/common/drivers/redshift/__init__.py
core/common/drivers/redshift/configuration.py
core/common/drivers/redshift/dialect.py
core/common/drivers/redshift/driver.py
core/common/drivers/snowflake/__init__.py
core/common/drivers/snowflake/configuration.py
core/common/drivers/snowflake/dialect.py
core/common/drivers/snowflake/driver.py
core/common/reporter/__init__.py
core/common/reporter/notifications.py
core/common/reporter/formatters/__init__.py
core/common/reporter/formatters/base.py
core/common/reporter/formatters/failures.py
core/common/reporter/formatters/progress.py
core/common/reporter/formatters/text.py
core/monitor/__init__.py
core/monitor/compiler.py
core/monitor/runner.py
core/monitor/analyzer/__init__.py
core/monitor/analyzer/data.py
core/monitor/analyzer/schema.py
core/monitor/analyzer/threshold.py
core/monitor/analyzer/zscore.py
core/monitor/models/__init__.py
core/monitor/models/base.py
core/monitor/models/custom.py
core/monitor/models/metrics.py
core/monitor/models/schedule.py
core/monitor/models/schema.py
core/monitor/models/table.py
core/monitor/tasks/__init__.py
core/monitor/tasks/base.py
core/monitor/tasks/profile.py
core/monitor/tasks/run.py
scheduler/__init__.py
scheduler/base.py
scheduler/constants.py
scheduler/db.py
scheduler/job.py
scheduler/manager.py
scheduler/handlers/__init__.py
scheduler/handlers/executions.py
scheduler/models/__init__.py
monosi-0.0.3.post2.dist-info/LICENSE
monosi-0.0.3.post2.dist-info/METADATA
monosi-0.0.3.post2.dist-info/WHEEL
monosi-0.0.3.post2.dist-info/entry_points.txt
monosi-0.0.3.post2.dist-info/top_level.txt
monosi-0.0.3.post2.dist-info/RECORD
