Metadata-Version: 2.1
Name: monosi
Version: 0.0.3.post2
Summary: Monosi - Data observability & monitoring toolkit
Home-page: https://github.com/monosidev/monosi
Author: Vocable Inc.
Author-email: support@monosi.dev
License: Apache License
Platform: UNKNOWN
License-File: LICENSE
Requires-Dist: Flask (==2.0.2)
Requires-Dist: Flask-APScheduler (==1.12.2)
Requires-Dist: Flask-Cors (==3.0.10)
Requires-Dist: Flask-RESTful (==0.3.9)
Requires-Dist: Flask-SQLAlchemy (==2.5.1)
Requires-Dist: psycopg2 (==2.9.3)
Requires-Dist: PyYAML (==6.0)
Requires-Dist: redshift-connector (==2.0.903)
Requires-Dist: snowflake-sqlalchemy (==1.3.3)
Requires-Dist: snowplow-tracker (==0.10.0)
Requires-Dist: sqlalchemy-redshift (==0.8.9)
